{
  "$schema": "../gen/schemas/desktop-schema.json",
  "identifier": "default",
  "description": "Capability for the main window",
  "windows": ["main", "riot-auth"],
  "permissions": [
    "core:default",
    "core:window:allow-create",
    "core:window:allow-close",
    "core:webview:allow-create-webview-window",
    "opener:default",
    "dialog:default",
    "fs:default",
    "fs:allow-write-text-file",
    "autostart:allow-enable",
    "autostart:allow-disable",
    "autostart:allow-is-enabled",
    "mcp-bridge:default",
    "log:default"
  ]
}
